README.rst
setup.py
wsgiadapter.py
requests_wsgi_adapter.egg-info/PKG-INFO
requests_wsgi_adapter.egg-info/SOURCES.txt
requests_wsgi_adapter.egg-info/dependency_links.txt
requests_wsgi_adapter.egg-info/requires.txt
requests_wsgi_adapter.egg-info/top_level.txt