Metadata-Version: 1.1
Name: requests-wsgi-adapter
Version: 0.2.2
Summary: WSGI Transport Adapter for Requests
Home-page: https://github.com/seanbrant/requests-wsgi-adapter
Author: Sean Brant
Author-email: brant.sean@gmail.com
License: BSD
Platform: UNKNOWN
Classifier: Development Status :: 4 - Beta
Classifier: Environment :: Web Environment
Classifier: Intended Audience :: Developers
Classifier: License :: OSI Approved :: BSD License
Classifier: Operating System :: OS Independent
Classifier: Programming Language :: Python
